distask/__init__.py
distask/events.py
distask/task.py
distask/util.py
distask/datastores/base.py
distask/datastores/mongodb.py
distask/datastores/redis.py
distask/locks/__init__.py
distask/locks/base.py
distask/locks/rl_lock.py
distask/locks/zk_lock.py
distask/schedulers/background.py
distask/schedulers/base.py
distask/serializers/base.py
distask/serializers/json.py
distask/serializers/pickle.py
distask/tiggers/base.py
distask/tiggers/delay.py
distask/tiggers/interval.py
distask/tiggers/cron/__init__.py
distask/tiggers/cron/expressions.py
distask/tiggers/cron/fields.py
distask-0.1.12.dist-info/LICENSE
distask-0.1.12.dist-info/METADATA
distask-0.1.12.dist-info/WHEEL
distask-0.1.12.dist-info/top_level.txt
distask-0.1.12.dist-info/RECORD
