Metadata-Version: 2.1
Name: distask
Version: 0.1.12
Summary: a distribute task scheduler 
Home-page: https://github.com/tickbh/distask
Author: tickbh
Author-email: tickdream125@hotmail.com
License: MIT Licence
Keywords: distribute scheduling cron
Platform: any
Requires-Python: >=3.6
License-File: LICENSE
Requires-Dist: tzlocal
Requires-Dist: pytz
Requires-Dist: kazoo
Requires-Dist: redlock
Requires-Dist: pymongo
Provides-Extra: extra
